Metadata-Version: 1.0
Name: vim2vsc
Version: 0.1.0
Summary: Python command line application to convert vimrc to vscode compatible bindings.
Home-page: http://gehrcke.de/2014/02/distributing-a-python-command-line-application
Author: Devanshu Desai
Author-email: dbdesai@ucsd.edu
License: UNKNOWN
Platform: UNKNOWN
